kw/__init__.py
kw/cache/__init__.py
kw/cache/aio.py
kw/cache/base.py
kw/cache/dbcache.py
kw/cache/helpers.py
kw/cache/json.py
kw/cache/utils.py
test/__init__.py
test/integration/__init__.py
test/integration/conftest.py
test/integration/py2/__init__.py
test/integration/py2/conftest.py
test/integration/py2/test_dbcache.py
test/integration/py2/test_kiwicache.py
test/integration/py3/__init__.py
test/integration/py3/conftest.py
test/integration/py3/test_aiokiwicache.py
test/unit/__init__.py
test/unit/conftest.py
test/unit/test_base.py
test/unit/test_dict.py
kiwi_cache-0.4.5.dist-info/METADATA
kiwi_cache-0.4.5.dist-info/WHEEL
kiwi_cache-0.4.5.dist-info/top_level.txt
kiwi_cache-0.4.5.dist-info/RECORD
